django_app/__init__.py
django_app/manage.py
django_app/settings.py
django_app/urls.py
django_app/wsgi.py
django_app/app/__init__.py
django_app/app/admin.py
django_app/app/apps.py
django_app/app/models.py
django_app/app/utils.py
django_app/app/views.py
django_app/app/management/__init__.py
django_app/app/management/commands/__init__.py
django_app/app/management/commands/perf_test.py
django_app/app/migrations/0001_initial.py
django_app/app/migrations/0002_auto_20200619_1313.py
django_app/app/migrations/0002_remove_biginteger_integer.py
django_app/app/migrations/0003_auto_20200620_1301.py
django_app/app/migrations/0004_auto_20200620_1302.py
django_app/app/migrations/__init__.py
django_app/app/tests/__init__.py
django_app/app/tests/big_integer.py
django_app/app/tests/binary.py
django_app/app/tests/boolean.py
django_app/app/tests/char.py
django_app/app/tests/date.py
django_app/app/tests/datetime.py
django_app/app/tests/decimal.py
django_app/app/tests/float.py
django_app/app/tests/foreign_key.py
django_app/app/tests/generic_ip_address.py
django_app/app/tests/integer.py
django_app/app/tests/many_to_many.py
django_app/app/tests/null_boolean.py
django_app/app/tests/one_to_one.py
django_app/app/tests/positive_integer.py
django_app/app/tests/positive_small_integer.py
django_app/app/tests/slug.py
django_app/app/tests/small_integer.py
django_app/app/tests/text.py
django_app/app/tests/time.py
django_app/app/tests/uuid.py
django_tarantool/__init__.py
django_tarantool/backend/__init__.py
django_tarantool/backend/base.py
django_tarantool/backend/client.py
django_tarantool/backend/creation.py
django_tarantool/backend/features.py
django_tarantool/backend/introspection.py
django_tarantool/backend/operations.py
django_tarantool/backend/schema.py
django_tarantool/backend/utils.py
django_tarantool-0.0.9.dist-info/METADATA
django_tarantool-0.0.9.dist-info/WHEEL
django_tarantool-0.0.9.dist-info/top_level.txt
django_tarantool-0.0.9.dist-info/RECORD
