Metadata-Version: 2.1
Name: django-tarantool
Version: 0.0.9
Summary: Tarantool database backend for Django
Home-page: https://github.com/artembo/django-tarantool
Author: Artem Morozov
Author-email: artembo@me.com
License: UNKNOWN
Platform: UNKNOWN
Classifier: Programming Language :: Python :: 3
Classifier: License :: OSI Approved :: MIT License
Classifier: Operating System :: OS Independent
Requires-Python: >=3.6
